{
  "id": "final-trial-readiness-review",
  "name": "final-trial-readiness-review",
  "title": "Final Trial Readiness Review",
  "description": "Run final local trial readiness checks and capture GitHub/CI follow-up status.",
  "status": "completed",
  "dev_type": null,
  "scope": null,
  "package": null,
  "priority": "P2",
  "creator": "suixingchen",
  "assignee": "suixingchen",
  "createdAt": "2026-05-27",
  "completedAt": "2026-05-27",
  "branch": null,
  "base_branch": "master",
  "worktree_path": null,
  "commit": null,
  "pr_url": null,
  "subtasks": [],
  "children": [],
  "parent": "05-27-rag-trial-operations-feedback-hardening",
  "relatedFiles": [],
  "notes": "",
  "meta": {}
}